h5/__about__.py
h5/__init__.py
h5/__main__.py
h5/_info.py
h5/_types.py
h5/cli.py
h5/core.py
h5/dev.py
h5/legacy.py
h5/py.typed
h5/testing.py
h5-0.12.1.dist-info/WHEEL
h5-0.12.1.dist-info/entry_points.txt
h5-0.12.1.dist-info/METADATA
h5-0.12.1.dist-info/RECORD
