Metadata-Version: 2.3
Name: h5
Version: 0.12.1
Summary: H5py utils
Keywords: h5,h5py,hdf5,numpy
Author: jesse
Author-email: jesse <jesse@dgi.com>
Classifier: Development Status :: 5 - Production/Stable
Classifier: Intended Audience :: Developers
Classifier: License :: OSI Approved :: MIT License
Classifier: Programming Language :: Python
Classifier: Programming Language :: Python :: 3 :: Only
Classifier: Programming Language :: Python :: 3.11
Classifier: Programming Language :: Python :: 3.12
Classifier: Programming Language :: Python :: 3.13
Classifier: Programming Language :: Python :: 3.14
Classifier: Typing :: Typed
Requires-Dist: h5py>=3.7
Requires-Dist: numpy>=1.23.2
Requires-Dist: click>=8.2.1 ; extra == 'cli'
Requires-Dist: rich>=14.1 ; extra == 'cli'
Requires-Dist: ry>=0.0.57 ; extra == 'cli'
Requires-Python: >=3.11, <4.0
Project-URL: Homepage, https://github.com/dynamic-graphics-inc/dgpy-libs/tree/main/libs/h5
Project-URL: Repository, https://github.com/dynamic-graphics-inc/dgpy-libs
Provides-Extra: cli
